pytestcwd/__init__.py
pytestcwd/__main__.py
pytestcwd-0.1.0.dist-info/LICENSE
pytestcwd-0.1.0.dist-info/METADATA
pytestcwd-0.1.0.dist-info/WHEEL
pytestcwd-0.1.0.dist-info/entry_points.txt
pytestcwd-0.1.0.dist-info/top_level.txt
pytestcwd-0.1.0.dist-info/RECORD
