Metadata-Version: 2.1
Name: pytestcwd
Version: 0.1.0
Summary: UNKNOWN
Home-page: https://github.com/andersonbrands/pytestcwd
Author: Anderson Brandao
Author-email: anderson.brands@gmail.com
License: UNKNOWN
Platform: UNKNOWN
Classifier: Programming Language :: Python :: 3
Requires-Python: >=3.6
Requires-Dist: pytest
